{
  "name": "Internal test",
  "email": "ricejessica@example.org",
  "last_name": "Clark",
  "company_name": "Dizzain",
  "job_title": "QA",
  "area_of_int": "Paid Social",
  "m_dig_spend": "N/A; Just want to chat",
  "country": "United States",
  "state": "Maryland",
  "text_c": "Cut expect read type a between. Ahead need get human significant figure inside. We grow pick somebody.\nCouple citizen different others poor position ability. Report see through partner.",
  "how_heard": "Other",
  "other": "Page grow ever story recent. Garden though would wish bill call low finish. Deep such experience certainly let remember."
}