{
  "name": "Internal test",
  "email": "williamsmith@example.com",
  "last_name": "Cohen",
  "company_name": "Dizzain",
  "job_title": "QA",
  "area_of_int": "Retail Media",
  "m_dig_spend": "$300K-$500K USD per month",
  "country": "United States",
  "state": "Pennsylvania",
  "text_c": "These eat none serious investment likely defense. Enter list thought open really find.\nFear peace cover none first under. Beautiful other several system require off natural.",
  "how_heard": "Other",
  "other": "Minute everyone himself red difference professional. Military different generation style."
}